README.md
setup.cfg
setup.py
Topsis_anshul_101903280.egg-info/PKG-INFO
Topsis_anshul_101903280.egg-info/SOURCES.txt
Topsis_anshul_101903280.egg-info/dependency_links.txt
Topsis_anshul_101903280.egg-info/top_level.txt
anshul/__init__.py
anshul/topsis.py