Metadata-Version: 2.1
Name: Topsis-anshul-101903280
Version: 0.0.1
Summary: Topsis
Home-page: UNKNOWN
Author: Anshul
Author-email: <ajakhar_be19@thapar.edu>
License: UNKNOWN
Keywords: python,Topsis
Platform: UNKNOWN
Classifier: Development Status :: 1 - Planning
Classifier: Intended Audience :: Developers
Classifier: Programming Language :: Python :: 3
Classifier: Operating System :: Unix
Classifier: Operating System :: MacOS :: MacOS X
Classifier: Operating System :: Microsoft :: Windows
